celery_extra_schedulers-0.1.1.dist-info/DESCRIPTION.rst
celery_extra_schedulers-0.1.1.dist-info/METADATA
celery_extra_schedulers-0.1.1.dist-info/RECORD
celery_extra_schedulers-0.1.1.dist-info/WHEEL
celery_extra_schedulers-0.1.1.dist-info/metadata.json
celery_extra_schedulers-0.1.1.dist-info/top_level.txt
celery_schedulers/__init__.py
celery_schedulers/redis.py
